{
  "schemaVersion": "1.0.0",
  "taskId": "TASK-M0A-002",
  "revision": 1,
  "status": "ready",
  "changeId": "CHG-2026-001-macos-m0a",
  "changeRevision": 1,
  "approvalId": "APR-TASK-M0A-002-R1",
  "coreBaseline": {
    "id": "CORE",
    "version": "1.0.0",
    "sha256": "adc03fa950c2eb4758d14c63985ce0b318b00dbbcb91006e0d18b0400b73252a"
  },
  "platformProfile": {
    "id": "PLATFORM-MACOS",
    "version": "0.1.0",
    "sha256": "54bd9b295799cb8d93bf397eeb585f24828463f4f1fce1e59a0693f65369d0bf"
  },
  "integrationProfiles": [
    {
      "id": "OPENHARMONY-TOOLS",
      "version": "0.1.0",
      "sha256": "679874cf44234a00b7e5d8f920e81c6b52ff489df2a2c8dd6f03b540c87a11e1"
    }
  ],
  "conformanceSuite": {
    "id": "CORE-CONFORMANCE-1.0.0",
    "sha256": "2e5a51bf78afc2e15a8cd989c9381fcc2ac2b7cce370c2bc545767df06419aa2"
  },
  "baseRevision": "e56fea2983192a96e394783021bf2026b75527db",
  "platform": "macos",
  "objective": "Implement ProcessExecutor and external-first HDC discovery prototypes with semantic-result fixtures.",
  "requirementRefs": [
    "PORT-PROCESS-001",
    "REQ-JOB-005",
    "REQ-NFR-002",
    "REQ-HDC-001"
  ],
  "acceptanceRefs": [
    "AC-JOB-005-01",
    "AC-NFR-002-01",
    "AC-HDC-001-01",
    "AC-HDC-001-02",
    "MAC-M0A-PROC-001",
    "MAC-M0A-HDC-001"
  ],
  "dependsOn": [
    "TASK-M0A-001"
  ],
  "allowedPaths": [
    "Packages/ArkDeckKit/Sources/ArkDeckProcess/**",
    "Packages/ArkDeckKit/Sources/ArkDeckOpenHarmony/**",
    "Packages/ArkDeckKit/Tests/ArkDeckProcessTests/**",
    "Packages/ArkDeckKit/Tests/ArkDeckOpenHarmonyTests/**",
    "Packages/ArkDeckKit/Tests/Fixtures/**",
    "openspec/changes/chg-2026-001-macos-m0a/evidence/**"
  ],
  "forbiddenPaths": [
    "openspec/constitution.md",
    "openspec/specs/**",
    "openspec/contracts/**",
    "openspec/baselines/**"
  ],
  "exclusiveResources": [],
  "risk": "medium",
  "executionEnvironment": "standardAgent",
  "runtimeCapabilities": [
    "repositoryProcess",
    "externalToolExecution"
  ],
  "hardwareRequirement": "none",
  "deliverables": [
    "Argument-array ProcessExecutor prototype with separated streams, timeout and cancellation.",
    "External-first HDC candidate discovery and immutable per-Job toolchain snapshot prototype.",
    "Semantic HDC success/failure fixtures including exit-zero failure output and large streaming data."
  ],
  "verification": [
    {
      "acceptanceId": "AC-JOB-005-01",
      "testId": "TEST-AC-JOB-005-01",
      "method": "processContract",
      "expectedEvidence": "Each value is one argv element and no shell expansion occurs.",
      "minimumEvidence": "contract",
      "fixtureRefs": []
    },
    {
      "acceptanceId": "AC-NFR-002-01",
      "testId": "TEST-AC-NFR-002-01",
      "method": "boundedMemoryContract",
      "expectedEvidence": "Peak memory remains within the declared fixed streaming window.",
      "minimumEvidence": "platform",
      "fixtureRefs": []
    },
    {
      "acceptanceId": "AC-HDC-001-01",
      "testId": "TEST-AC-HDC-001-01",
      "method": "toolchainContract",
      "expectedEvidence": "The Job retains the selected absolute path, hash, version, endpoint and generation.",
      "minimumEvidence": "contract",
      "fixtureRefs": []
    },
    {
      "acceptanceId": "AC-HDC-001-02",
      "testId": "TEST-AC-HDC-001-02",
      "method": "toolchainDiagnosticsContract",
      "expectedEvidence": "The prototype exposes every required toolchain diagnostic field and marks unavailable values unknown/unverified.",
      "minimumEvidence": "platform",
      "fixtureRefs": []
    },
    {
      "acceptanceId": "MAC-M0A-PROC-001",
      "testId": "TEST-MAC-M0A-PROC-001",
      "method": "ProcessExecutor Port contract suite.",
      "expectedEvidence": "argv, stream, timeout, cancellation and process cleanup checks all pass.",
      "minimumEvidence": "platform",
      "fixtureRefs": []
    },
    {
      "acceptanceId": "MAC-M0A-HDC-001",
      "testId": "TEST-MAC-M0A-HDC-001",
      "method": "Installed-tool discovery and semantic-failure matrix.",
      "expectedEvidence": "Path, version, source, trust metadata and semantic failures are deterministically classified.",
      "minimumEvidence": "platform",
      "fixtureRefs": []
    }
  ],
  "stopConditions": [
    "AC-HDC-005-01 has no approved parser fixture pinned by the accepted Integration lock and conformance suite.",
    "Implementation requires a host shell or string-built command line.",
    "An unknown HDC output is treated as success or a Job toolchain can change after creation.",
    "A required external tool execution entitlement or distribution decision is not yet approved."
  ]
}
